revivelink_bypass/__init__.py
revivelink_bypass/link.py
revivelink_bypass/py.typed
revivelink_bypass/version.py
revivelink_bypass/tests/__init__.py
revivelink_bypass/tests/conftest.py
revivelink_bypass/tests/link_test.py
revivelink_bypass-0.0.2.dist-info/LICENSE
revivelink_bypass-0.0.2.dist-info/METADATA
revivelink_bypass-0.0.2.dist-info/WHEEL
revivelink_bypass-0.0.2.dist-info/top_level.txt
revivelink_bypass-0.0.2.dist-info/RECORD
