Metadata-Version: 2.1
Name: revivelink-bypass
Version: 0.0.2
Summary: UNKNOWN
Home-page: https://gitlab.com/florentclarret/revivelink-bypass
Author: Florent Clarret
Author-email: florent.clarret@gmail.com
License: MIT
Project-URL: Changelog, https://github.com/FlorentClarret/revivelink-bypass/blob/main/CHANGELOG.md
Platform: UNKNOWN
Classifier: License :: OSI Approved :: MIT License
Classifier: Programming Language :: Python :: 3
Classifier: Programming Language :: Python :: 3.7
Classifier: Programming Language :: Python :: 3.8
Classifier: Programming Language :: Python :: 3.9
Classifier: Programming Language :: Python :: 3.10
Classifier: Programming Language :: Python :: 3.11
License-File: LICENSE
Requires-Dist: beautifulsoup4 (==4.11.1)
Requires-Dist: requests (==2.28.1)
